{
  "data" : {
    "id" : "622592",
    "type" : "groups",
    "attributes" : {
      "openToAll" : true,
      "createdAt" : 1498746616238,
      "name" : "agroup",
      "description" : "agroupdescription",
      "thumbUrl" : "abc",
      "dtoAction" : null,
      "dtoApplyTo" : null
    },
    "relationships" : {
      "creator" : {
        "links" : {
          "self" : "http://localhost:88/jsonapi/groups/622592/relationships/creator",
          "related" : "http://localhost:88/jsonapi/groups/622592/creator"
        }
      },
      "members" : {
        "links" : {
          "self" : "http://localhost:88/jsonapi/groups/622592/relationships/members",
          "related" : "http://localhost:88/jsonapi/groups/622592/members"
        }
      },
      "receivedPosts" : {
        "links" : {
          "self" : "http://localhost:88/jsonapi/groups/622592/relationships/receivedPosts",
          "related" : "http://localhost:88/jsonapi/groups/622592/receivedPosts"
        }
      }
    },
    "links" : {
      "self" : "http://localhost:88/jsonapi/groups/622592"
    }
  }
}